regexkit/__init__.py
regexkit/patterns.py
regexkit/regexkit.py
regexkit-0.1.dist-info/licenses/LICENSE
tests/__init__.py
tests/test_patterns.py
regexkit-0.1.dist-info/METADATA
regexkit-0.1.dist-info/WHEEL
regexkit-0.1.dist-info/top_level.txt
regexkit-0.1.dist-info/RECORD
