Metadata-Version: 2.4
Name: regexkit
Version: 0.1
Summary: simplify the creation of regular expressions using a fluent interface
Home-page: https://github.com/Ali-TM-original/regexkit
Author: Ali-TM-original
License: MIT
Classifier: Programming Language :: Python :: 3
Classifier: License :: OSI Approved :: MIT License
Classifier: Operating System :: OS Independent
License-File: LICENSE
Dynamic: author
Dynamic: classifier
Dynamic: description
Dynamic: description-content-type
Dynamic: home-page
Dynamic: license
Dynamic: license-file
Dynamic: summary
